{"id":"975647c2-05f8-434a-81f6-b852ec2f067a","timestamp":1766225354071,"matcher":{"static":{},"wildcard":{},"dynamic":{}},"prerendered":["/","/en","/en/latest-books","/latest-books","/purchase-link","/my-books","/en/purchase-link","/en/new-book","/new-book","/en/my-books","/en/sales-pos","/sales-pos","/en/settings","/settings","/en/readers","/readers","/affiliation-link","/en/affiliation-link","/batch-short-links","/en/batch-short-links","/en/batch-qrcode","/batch-qrcode","/en/sales-report","/sales-report","/en/settings/connect/return","/settings/connect/return","/en/settings/connect/refresh","/settings/connect/refresh"]}